{"wishlist-group-product":"Prodotto","product-other-dimensions":"Altre dimensioni","com-eyewear-printed":"Stampato","product-shape":"Forma/Forme","wishlist-update":"La wishlist è stata modificata","products-gridlink-bel":"Cinture","com-eyewear-blue-light":"Luce blu","product-materials":"{count} Materiali","news-sheet-next-page":"SUCCESSIVO","news-sheet-previous-page":"PRECEDENTE","products-gridlink-dresses":"Abiti","grid-pages":"Stories","products-gridlink-jackets":"Occhiali da sole","footer-legal":"Informazioni legali","com-podcast-see-more":"Vedere di più","products-gridlink-hat":"Cappelli","product-declination":"Variation","com-looksheet-video-stop":"Stop ","product-category-eyeglasses":"Occhiali da vista","com-lens-width":"Lens width","com-eyewear-temple-dim":"Temple length","wishlist-title":"Wishlist","grid-product":"{{N}}  Prodotto","com-video-play":"Riprodurre video decorativi","looksheet-back-hc":"Tutti i look","com-search-quicks-links":"Suggerimenti","products-gridlink-opt":"Occhiali da vista","com-care-services":"Consigli & Servizi","com-search-multi-result-in":"N]] risultati nel {{X","products-gridlink-sho":"Calzature","eyewear-manufacture":"Made in Italy","products-searched-email":"Email","product-other-fabrics":"Altro materiale","global-view-details":"Maggiori dettagli","products-find-store":"Punti vendita","product-diameter":"Diametro: {diameter} {unit}","search-find-btq":"Punti vendita","look-title-hc":"Look","eyewear-uva-protection":"Protezione 100% UVA - UVB CE","com-product-size-l":"Large","com-product-size-m":"Medium","products-gridlink-sun":"Tutti gli occhiali","com-subnavigation-care-and-services":"Consigli & Servizi","grid-see-previous":"Prodotti precedenti","eyewear-front-view":"Vista frontale","product-related-products":"Prodotti simili","search":"Ricerca","com-product-size-s":"Small","com-search-delete":"Cancellare","page-number":"Pagina {{N}}","look-title-rtw":"Look","product-lipstick-mention":"Rossetto venduto separatamente","com-product-lens":"Lens width","com-slideshow-next-slide":"Next slide","retail-suggested-price":"Prezzo raccomandato","com-grid-products":"{{N}} prodotti","com-slideshow-img-alt":"Media","search-all-results":"Tutti i risultati","global-see-previous":"Prodotti precedenti","popin-share-copy":"Copiare il link","products-gridlink-rtw":"Prêt-à-Porter","products-gridlink-pullovers":"Cardigan & pull-over","wishlist-group-products":"Prodotti","popin-share-facebook":"FACEBOOK","products-more-details":"Maggiori dettagli","looksheet-back":"Tutti i look","look-know-more":"Per saperne di più (su questo look)","product-finish":"Finitura","eyewear-lenses-filter":"Lenses are UV Category Filter","com-search-recent":"Ultime ricerche","products-gridlink-hea":"Cappelli","last-products-viewed":"Ultimi prodotti visualizzati","com-product-lenses":"Lens height","recommended-retail-price":"Prezzo raccomandato. Per informazioni legali ","navigation-menu":"Menu","product-colors":"{count} Colori","eyewear-side-view":"Vista laterale","wishlist-item-removed":"I prodotti non più presenti sul sito sono stati rimossi ","grid-products":"{{N}} prodotti","eyewear-fit-universal-content":"Disponibile in un'unica taglia.","grid-clear-filters":"Eliminare tutti i filtri","com-grid-pages":"Storie","com-slideshow-previous-slide":"Previous slide","products-gridlink-oth":"Altri accessori","product-label-nose-bridge-low":"con naselli integrati, particolarmente adatti a chi ha un ponte nasale basso.","popin-share-twitter":"TWITTER","products-try":"Try on","product-in-the-campaign":"Nella campagna pubblicitaria","navigation-products-viewed":"Ultimi prodotti visualizzati","search-placeholder":"Ricerca","products-gridlink-slg":"Piccola pelletteria","products-searched-error":"Nessun risultato per \"xx\". \n\nHa una domanda?","news-next-page":"PAGINA SUCCESSIVA","com-slideshow-last-slide":"Last slide","product-dimensions":"Dimensioni","footer-explore":"Visitare CHANEL.com","com-search-one-result-in":"1 risultato nel X","look-collection-available-soon":"Prossimamente in boutique","00-test-fashioncom":"00-test-fashioncom-en","com-news-next-page":"PAGINA SUCCESSIVA","store-label":"In boutique","wishlist-group-looks":"Look","com-slideshow-first-slide":"First slide","products-compare":"Compare","product-price-tax-label":" ","products-searched-call":"Telefono","products-declination":"Varianti","look-title-show":"Look","product-category":"Categoria","product-price-under-request":"Prezzo su richiesta","looksheet-product-detail":"Maggiori dettagli","popin-share-title":"Condividere","whishlist-share":"Condividere la wishlist","product-lense-size":"Dimensione/i lenti","explore-look":"Scoprire il look","products-gridlink-hdb":"Tutte le borse","products-grid-bel":"Cinture","fashion-shows-collection-presentation":"L'ultima sfilata e<br/>la presentazione della Collezione","wishlist-empty":"La sua wish list è vuota","product-reference":"Referenza","com-size-guide-button":"Guida alle taglie","products-gridlink-cjy":"Bijoux","fap-look-ref-short":"Ref :","com-eyewear-transparent":"Trasparente","product-prescription-friendly":"Predisposizione per lenti graduate","com-made-in-alt":"Fabbricato in ","wishlist-group-eyewear":"Occhiali","looksheet-share-hc":"Condividere l'uscita","com-more-variations":"Molteplici varianti","com-see-product-details-look-page":"See the details","products-gridlink-skirts":"Gonne","view-wishlist":"Vedere la wishlist","global-view-more":"Prodotti seguenti","product-fits":"Modelli","products-universal":"Universale","collections":"Collezioni","grid-apply-filters":"Applicare il filtro","product-mirror":"Specchiato","wishlist-item-deleted":"L'articolo è stato eliminato dalla wishlist. Annullare","popin-share-email":"Email","product-other-colors":"Altri colori","looksheet-share":"Condividere il look","product-features":"Caratteristiche","popin-share-copy-confirmation":"Il link è stato copiato","product-other-materials":"Altri Materiali","pants-shorts":"Pantaloni & Tute","global-see-all":"Vedere tutto","products-cart":"Aggiungere al carrello","mention-advisor":"Contatti","product-fit":"Modello","com-search-close":"Chiudere","com-lense-width":"Ampiezza delle lenti","footer-services":"Consigli & Servizi","news-previous-page":"PAGINA PRECEDENTE","fashion-shows-label":"L'ultima sfilata e la presentazione della Collezione","looksheet-back-hc-passages":"Tutte le uscite","com-eyewear-front-dim":"Frame width","wishlist-access-message":"Per accedere alla wishlist da qualsiasi dispositivo, creare un account ed effettuare il login","products":"Prodotti","wishlist-message-information":"Aggiungere prodotti e look alla wishlist da condividere","products-gridlink-top":"Bluse & top","search-empty-title":"Ricerca-Nessun risultato per \"{{terms}}\"","products-gridlink-knitwear":"Maglieria","com-see-details-look-page":"See the look details","com-grid-services":"Consigli & Servizi","product-gradient-plural":"Graduati","passage-title-hc":"Uscita","footer-chanel-fondation":"Fondation CHANEL","product-color":"Colore","product-in-the-show":"Nella sfilata","product-gradient":"Graduato","com-looksheet-video-play":"Play","wishlist-group-look":"Look","products-alternative":"Alternativi","more-informations":"cliccare qui.","com-looksheet-video-pause":"Pause","products-standard":"Standard","looksheet-notified":"Prossimamente in boutique","com-eyewear-lens-dim":"Lens width","product-heel-height":"Altezza tacco {heel} {unit}","legal-information-link":"#legal/6-prezzi","footer-house":"Maison CHANEL","products-gridlink-sca":"Sciarpe","products-gridlink-pants":"Pantaloni & short","last-looks-viewed":"Ultimi look visualizzati","share-campaign":"Condividere la campagna ","com-search-one-result-i":"1 risultato nel X","product-polarized-plural":"Polarizzati","grid-view-more":"Prodotti seguenti","product-frame":"Montatura","product-matte":"Opaco","product-lenses":"Lenti","product-matte-plural":"Opachi","products-gridlink-glo":"Guanti","com-product-glitter":"Glitter","com-news-previous-page":"PAGINA PRECEDENTE","products-searched-error-firstline":"Nessun risultato per \"{{terms}}\". ","grid-refine":"Filtrare","product-polarized":"Polarizzato","products-more-pieces":"Una selezione piu’ ampia in boutique","com-made-in":"Fabbricato in ","product-ref":"Referenza:","com-size-guide":"Guida alle taglie","chanel-mode":"CHANEL Moda","wishlist-share":"Condividere la wishlist","com-wishlist-unavailable":"Products that are not displayed on the website anymore have been removed","product-category-sunglasses":"Occhiali da sole","search-title":"{{terms}}-Search resultats","com-legal-uk":"Subject to availability. To contact our boutiques <a href=\"#storelocator/fsh\">click here</a>","com-video-pause":"Pausar video decorativi","product-mirror-plural":"Specchiati","not-now-mention":"Non ora","products-gridlink-cam":"Camelie","products-searched-chat":"Chat","com-eyewear-bridge-dim":"Bridge width","wishlist-group-accessories":"Accessori","com-search-clear":"Cancellare","products-gridlink-outerwear":"Mantelle","cta-shop-online":"Shop online","optical-price-mention":"Disponibile esclusivamente da rivenditori autorizzati CHANEL ","ok":"OK","products-searched-error-secondline":"Ha una domanda?","product-material":"Materiale","com-eyewear-height-dim":"Lens height","mention-legal":"Informazioni legali","product-label-fit-faces":"adatti a tutti i tipi di viso."}